gavtk/Binomialdistribution.py
gavtk/Gaussiandistribution.py
gavtk/Generaldistribution.py
gavtk/__init__.py
gavtk-0.6.dist-info/METADATA
gavtk-0.6.dist-info/WHEEL
gavtk-0.6.dist-info/top_level.txt
gavtk-0.6.dist-info/RECORD
