Metadata-Version: 2.1
Name: gavtk
Version: 0.6
Summary: Graph Analysis and Visualization ToolKit
Home-page: UNKNOWN
Author: Abhishek kumar Singh
Author-email: abhishekkmr2000@gmail.com
License: UNKNOWN
Platform: UNKNOWN
